uipath/dev/__init__.py
uipath/dev/__mock__.py
uipath/dev/py.typed
uipath/dev/infrastructure/__init__.py
uipath/dev/infrastructure/logging_handlers.py
uipath/dev/infrastructure/tracing_exporter.py
uipath/dev/models/__init__.py
uipath/dev/models/chat.py
uipath/dev/models/execution.py
uipath/dev/models/messages.py
uipath/dev/services/__init__.py
uipath/dev/services/debug_bridge.py
uipath/dev/services/run_service.py
uipath/dev/ui/panels/__init__.py
uipath/dev/ui/panels/_json_schema.py
uipath/dev/ui/panels/chat_panel.py
uipath/dev/ui/panels/new_run_panel.py
uipath/dev/ui/panels/run_details_panel.py
uipath/dev/ui/panels/run_history_panel.py
uipath/dev/ui/styles/terminal.tcss
uipath/dev/ui/widgets/json_input.py
uipath_dev-0.0.20.dist-info/METADATA
uipath_dev-0.0.20.dist-info/WHEEL
uipath_dev-0.0.20.dist-info/entry_points.txt
uipath_dev-0.0.20.dist-info/licenses/LICENSE
uipath_dev-0.0.20.dist-info/RECORD
