Metadata-Version: 2.4
Name: uipath-dev
Version: 0.0.20
Summary: UiPath Developer Console
Project-URL: Homepage, https://uipath.com
Project-URL: Repository, https://github.com/UiPath/uipath-dev-python
Project-URL: Documentation, https://uipath.github.io/uipath-python/
Maintainer-email: Cristian Pufu <cristian.pufu@uipath.com>
License-File: LICENSE
Classifier: Intended Audience :: Developers
Classifier: Programming Language :: Python :: 3.11
Classifier: Programming Language :: Python :: 3.12
Classifier: Programming Language :: Python :: 3.13
Classifier: Topic :: Software Development :: Build Tools
Requires-Python: >=3.11
Requires-Dist: pyperclip<2.0.0,>=1.11.0
Requires-Dist: textual<8.0.0,>=7.2.0
Requires-Dist: uipath-runtime<0.7.0,>=0.6.0
